Metadata-Version: 2.1
Name: django-dbtemplates-bakatrouble
Version: 2.0.2
Summary: Template loader for templates stored in the database
Home-page: https://django-dbtemplates.readthedocs.io/
Author: Jannis Leidel
Author-email: jannis@leidel.info
License: UNKNOWN
Platform: UNKNOWN
Classifier: Development Status :: 5 - Production/Stable
Classifier: Environment :: Web Environment
Classifier: Intended Audience :: Developers
Classifier: License :: OSI Approved :: BSD License
Classifier: Operating System :: OS Independent
Classifier: Programming Language :: Python
Classifier: Programming Language :: Python :: 2
Classifier: Programming Language :: Python :: 2.7
Classifier: Programming Language :: Python :: 3
Classifier: Programming Language :: Python :: 3.4
Classifier: Programming Language :: Python :: 3.5
Classifier: Framework :: Django
Requires-Dist: django-appconf (>=0.4)
